pyvigil/__init__.py
pyvigil-0.1.0.dist-info/licenses/LICENSE
pyvigil-0.1.0.dist-info/METADATA
pyvigil-0.1.0.dist-info/WHEEL
pyvigil-0.1.0.dist-info/top_level.txt
pyvigil-0.1.0.dist-info/RECORD
